LICENSE.txt
MANIFEST.in
README.rst
requirements-dev.txt
requirements.txt
setup.cfg
setup.py
gpsd_format/__init__.py
gpsd_format/_schema_def.py
gpsd_format/cli.py
gpsd_format/core.py
gpsd_format/drivers.py
gpsd_format/pycompat.py
gpsd_format/schema.py
gpsd_format/validate.py
gpsd_format.egg-info/PKG-INFO
gpsd_format.egg-info/SOURCES.txt
gpsd_format.egg-info/dependency_links.txt
gpsd_format.egg-info/entry_points.txt
gpsd_format.egg-info/requires.txt
gpsd_format.egg-info/top_level.txt
tests/__init__.py
tests/cmdtest.py
tests/sample_files.py
tests/test_compatibility.py
tests/test_core.py
tests/test_drivers.py
tests/test_schema.py
tests/test_schema_def.py
tests/test_validate.py