Metadata-Version: 1.0
Name: gpsd-format
Version: 0.0.3
Summary: A library and command line tool to read, write and validate AIS and GPS messages in the GPSD JSON format (or the same format in a msgpack container).
Home-page: https://github.com/SkyTruth/gpsd_format
Author: Egil Moeller, Kevin Wurster
Author-email: egil@skytruth.org, kevin@skytruth.org
License: GPL
Keywords: gpsd
Platform: UNKNOWN
